twosamplemr/__init__.py
twosamplemr/add_rsq.py
twosamplemr/eve.py
twosamplemr/harmonise.py
twosamplemr/heterogeneity.py
twosamplemr/instruments.py
twosamplemr/ld.py
twosamplemr/moe.py
twosamplemr/mr.py
twosamplemr/mr_grip.py
twosamplemr/mr_mode.py
twosamplemr/multivariable_mr.py
twosamplemr/query.py
twosamplemr/read_data.py
twosamplemr/rucker.py
twosamplemr/scatterplot.py
twosamplemr/steiger_filtering.py
twosamplemr/verifytoken.py
twosamplemr-0.1.3.dist-info/licenses/LICENSE
twosamplemr-0.1.3.dist-info/METADATA
twosamplemr-0.1.3.dist-info/WHEEL
twosamplemr-0.1.3.dist-info/top_level.txt
twosamplemr-0.1.3.dist-info/RECORD
