Metadata-Version: 2.4
Name: twosamplemr
Version: 0.1.3
Summary: Two-sample Mendelian randomization implemented in Python
Author-email: Jurica Matosic <jurica.juki.matosic@gmail.com>
Project-URL: Homepage, https://github.com/JuMa555/TwoSampleMR-Python
Project-URL: Repository, https://github.com/JuMa555/TwoSampleMR-Python
Requires-Python: >=3.8
License-File: LICENSE
Requires-Dist: pandas
Requires-Dist: numpy
Requires-Dist: scipy
Requires-Dist: matplotlib
Requires-Dist: seaborn
Requires-Dist: statsmodels
Requires-Dist: ieugwaspy
Requires-Dist: requests
Requires-Dist: dotenv
Dynamic: license-file
